[
  {
    "key": "19980116-08-005-003-12585",
    "label": "发生"
  },
  {
    "key": "19980116-08-005-003-12586",
    "label": "发生"
  },
  {
    "key": "19980116-08-005-003-12588",
    "label": "未发生"
  },
  {
    "key": "19980116-08-005-003-12589",
    "label": "其他"
  },
  {
    "key": "19980116-08-005-003-12590",
    "label": "其他"
  },
  {
    "key": "19980116-08-005-003-12591",
    "label": "其他"
  },
  {
    "key": "19980116-08-005-003-12592",
    "label": "未发生"
  },
  {
    "key": "19980116-08-005-003-12593",
    "label": "发生"
  },
  {
    "key": "19980116-08-005-003-12595",
    "label": "发生"
  },
  {
    "key": "19980116-08-005-003-12596",
    "label": "未发生"
  },
  {
    "key": "19980116-08-005-003-12597",
    "label": "发生"
  },
  {
    "key": "19980116-08-005-003-12598",
    "label": "未发生"
  },
  {
    "key": "19980116-08-005-003-12599",
    "label": "未发生"
  },
  {
    "key": "19980116-08-005-003-12600",
    "label": "未发生"
  },
  {
    "key": "19980116-08-005-003-12602",
    "label": "未发生"
  },
  {
    "key": "19980116-08-005-003-12603",
    "label": "未发生"
  }
]
