[
  {
    "key": "19980108-01-005-003-4194",
    "label": "发生"
  },
  {
    "key": "19980108-01-005-003-4195",
    "label": "发生"
  },
  {
    "key": "19980108-01-005-003-4196",
    "label": "发生"
  },
  {
    "key": "19980108-01-005-003-4197",
    "label": "发生"
  },
  {
    "key": "19980108-01-005-003-4198",
    "label": "发生"
  },
  {
    "key": "19980108-01-005-003-4199",
    "label": "发生"
  },
  {
    "key": "19980108-01-005-003-4200",
    "label": "其他"
  },
  {
    "key": "19980108-01-005-003-4201",
    "label": "其他"
  },
  {
    "key": "19980108-01-005-003-4202",
    "label": "发生"
  },
  {
    "key": "19980108-01-005-003-4203",
    "label": "发生"
  },
  {
    "key": "19980108-01-005-003-4205",
    "label": "其他"
  },
  {
    "key": "19980108-01-005-003-4207",
    "label": "未发生"
  },
  {
    "key": "19980108-01-005-003-4208",
    "label": "未发生"
  },
  {
    "key": "19980108-01-005-003-4209",
    "label": "未发生"
  },
  {
    "key": "19980108-01-005-003-4210",
    "label": "发生"
  },
  {
    "key": "19980108-01-005-003-4213",
    "label": "发生"
  },
  {
    "key": "19980108-01-005-003-4214",
    "label": "发生"
  },
  {
    "key": "19980108-01-005-003-4215",
    "label": "其他"
  },
  {
    "key": "19980108-01-005-003-4216",
    "label": "其他"
  },
  {
    "key": "19980108-01-005-003-4217",
    "label": "其他"
  },
  {
    "key": "19980108-01-005-003-4218",
    "label": "其他"
  },
  {
    "key": "19980108-01-005-003-4219",
    "label": "其他"
  },
  {
    "key": "19980108-01-005-003-4220",
    "label": "未发生"
  },
  {
    "key": "19980108-01-005-003-4221",
    "label": "其他"
  }
]
